fuad_namer/__init__.py
fuad_namer/namer.py
fuad_namer-1.0.0.dist-info/METADATA
fuad_namer-1.0.0.dist-info/WHEEL
fuad_namer-1.0.0.dist-info/top_level.txt
fuad_namer-1.0.0.dist-info/RECORD
