Metadata-Version: 2.1
Name: fuad-namer
Version: 1.0.0
Summary: A cool Bengali-English username generator
Home-page: https://github.com/yourusername/fuad-namer
Author: Mubtasim Fuad
Author-email: mubtasimfad64@gmail.com
Classifier: Programming Language :: Python :: 3
Classifier: Operating System :: OS Independent
Requires-Python: >=3.6
